calmjs.bower-1.0.2-py3.4-nspkg.pth
calmjs/__pycache__/__init__.pypy-22.pyc
calmjs/bower/__init__.py
calmjs/bower/__init__.pyc
calmjs/bower/__main__.py
calmjs/bower/__pycache__/__init__.cpython-34.pyc
calmjs/bower/__pycache__/__init__.pypy-22.pyc
calmjs/bower/__pycache__/__main__.cpython-34.pyc
calmjs/bower/tests/__init__.py
calmjs/bower/tests/__init__.pyc
calmjs/bower/tests/test_bower.py
calmjs/bower/tests/test_bower.pyc
calmjs/bower/tests/test_dist.py
calmjs/bower/tests/test_dist.pyc
calmjs/bower/tests/test_runtime.py
calmjs/bower/tests/test_runtime.pyc
calmjs/bower/tests/__pycache__/__init__.cpython-34.pyc
calmjs/bower/tests/__pycache__/__init__.pypy-22.pyc
calmjs/bower/tests/__pycache__/test_bower.cpython-34.pyc
calmjs/bower/tests/__pycache__/test_bower.pypy-22.pyc
calmjs/bower/tests/__pycache__/test_dist.cpython-34.pyc
calmjs/bower/tests/__pycache__/test_dist.pypy-22.pyc
calmjs/bower/tests/__pycache__/test_runtime.cpython-34.pyc
calmjs/bower/tests/__pycache__/test_runtime.pypy-22.pyc
calmjs.bower-1.0.2.dist-info/DESCRIPTION.rst
calmjs.bower-1.0.2.dist-info/METADATA
calmjs.bower-1.0.2.dist-info/RECORD
calmjs.bower-1.0.2.dist-info/WHEEL
calmjs.bower-1.0.2.dist-info/entry_points.txt
calmjs.bower-1.0.2.dist-info/metadata.json
calmjs.bower-1.0.2.dist-info/namespace_packages.txt
calmjs.bower-1.0.2.dist-info/package.json
calmjs.bower-1.0.2.dist-info/top_level.txt
