Metadata-Version: 2.0
Name: calmjs.bower
Version: 1.0.2
Summary: Bower support for the calmjs framework.
Home-page: https://github.com/calmjs/calmjs.bower
Author: Tommy Yu
Author-email: tommy.yu@auckland.ac.nz
License: gpl
Platform: UNKNOWN
Classifier: Development Status :: 5 - Production/Stable
Classifier: Environment :: Console
Classifier: Framework :: Setuptools Plugin
Classifier: Intended Audience :: Developers
Classifier: License :: OSI Approved :: GNU General Public License v2 or later (GPLv2+)
Classifier: Operating System :: OS Independent
Classifier: Programming Language :: JavaScript
Classifier: Programming Language :: Python :: 2.7
Classifier: Programming Language :: Python :: 3.3
Classifier: Programming Language :: Python :: 3.4
Classifier: Programming Language :: Python :: 3.5
Requires-Dist: calmjs (>=1.0.3)
